turnip_text-0.0.5.dist-info/METADATA
turnip_text-0.0.5.dist-info/WHEEL
turnip_text-0.0.5.dist-info/license_files/LICENSE-APACHE
turnip_text-0.0.5.dist-info/license_files/LICENSE-MIT
turnip_text/__init__.py
turnip_text/render/markdown/__init__.py
turnip_text/render/markdown/renderer.py
turnip_text/render/markdown/std_plugins.py
turnip_text/render/__init__.py
turnip_text/render/dyn_dispatch.py
turnip_text/render/counters.py
turnip_text/render/manual_numbering.py
turnip_text/render/latex/__init__.py
turnip_text/render/latex/renderer.py
turnip_text/render/latex/std_plugins.py
turnip_text/render/latex/backrefs.py
turnip_text/render/latex/setup.py
turnip_text/doc/__init__.py
turnip_text/doc/std_plugins.py
turnip_text/doc/user_nodes.py
turnip_text/doc/anchors.py
turnip_text/py.typed
turnip_text/build_system.py
turnip_text/__init__.pyi
turnip_text/helpers.py
turnip_text/system.py
turnip_text/_native.abi3.so
turnip_text-0.0.5.dist-info/RECORD
