Metadata-Version: 2.3
Name: turnip_text
Version: 0.0.5
Classifier: Programming Language :: Python :: 3
Classifier: License :: OSI Approved :: MIT License
Classifier: License :: OSI Approved :: Apache Software License
Classifier: Operating System :: OS Independent
Requires-Dist: mypy ; extra == 'typing'
Requires-Dist: black ; extra == 'fmt'
Requires-Dist: pytest ; extra == 'test'
Provides-Extra: typing
Provides-Extra: fmt
Provides-Extra: test
License-File: LICENSE-APACHE
License-File: LICENSE-MIT
Summary: Document description language that allows embedded Python to describe document structure
Author: Samuel Stark
Author-email: Samuel Stark <popgoestoast@gmail.com>
License: MIT OR Apache-2.0
Requires-Python: >=3.11
